dcss/__init__.py
dcss/bayes.py
dcss/networks.py
dcss/paths.py
dcss/plotting.py
dcss/status.py
dcss/svo.py
dcss/text.py
dcss/utils.py
dcss/writing_utilities.py
dcss-1.0.2.dist-info/LICENSE
dcss-1.0.2.dist-info/METADATA
dcss-1.0.2.dist-info/WHEEL
dcss-1.0.2.dist-info/top_level.txt
dcss-1.0.2.dist-info/RECORD
